{
  "Board size": 19,
  "Black stones": [
    "fp",
    "bo",
    "ap",
    "gq",
    "fr",
    "dn",
    "hp",
    "ho",
    "fm",
    "cn",
    "fo",
    "do",
    "dp",
    "dq",
    "es",
    "gn"
  ],
  "White stones": [
    "cp",
    "dm",
    "em",
    "fq",
    "er",
    "eq",
    "dr",
    "cr",
    "bp",
    "gr",
    "hr",
    "iq",
    "io",
    "ip",
    "hn",
    "im",
    "hl",
    "fl",
    "fk",
    "dk",
    "bl",
    "bj"
  ],
  "Labels": {},
  "Start": "B",
  "Solution": [
    "qc",
    "qb",
    "rb",
    "ra",
    "pe",
    "sb",
    "ne",
    "mg",
    "qh",
    "og",
    "pg",
    "nf"
  ],
  "Comments": "2D",
  "Other variations": [
    [
      "qc",
      "qb",
      "rb",
      "ra",
      "pe",
      "sb",
      "ne",
      "mg",
      "pg",
      "nf"
    ],
    [
      "qc",
      "qb",
      "rb",
      "ra",
      "sb",
      "sc",
      "pe",
      "sa",
      "ne",
      "mg",
      "qh",
      "og",
      "pg",
      "nf"
    ],
    [
      "qc",
      "qb",
      "rb",
      "ra",
      "sb",
      "sc",
      "pe",
      "sa",
      "ne",
      "mg",
      "pg",
      "nf"
    ],
    [
      "qc",
      "rb",
      "qb",
      "mb",
      "qh"
    ]
  ]
}